{"stats":{"minecraft:custom":{"minecraft:time_since_rest":22220,"minecraft:crouch_one_cm":1,"minecraft:play_time":22220,"minecraft:sprint_one_cm":76246,"minecraft:damage_taken":30,"minecraft:walk_one_cm":30117,"minecraft:sneak_time":77,"minecraft:mob_kills":2,"minecraft:jump":328,"minecraft:damage_dealt":460,"minecraft:leave_game":1,"minecraft:time_since_death":22220,"minecraft:walk_on_water_one_cm":228,"minecraft:total_world_time":23194,"minecraft:climb_one_cm":1198,"minecraft:interact_with_crafting_table":1,"minecraft:fall_one_cm":4393,"minecraft:fly_one_cm":152623},"minecraft:used":{"minecraft:dirt":1,"farmersdelight:netherite_knife":7,"minecraft:magenta_bed":2},"minecraft:picked_up":{"minecraft:wheat_seeds":3,"minecraft:bone_meal":1,"minecraft:dirt":1},"minecraft:mined":{"minecraft:grass_block":1,"minecraft:birch_log":1},"minecraft:killed":{"mca:male_villager":1,"mca:female_villager":1}},"DataVersion":3955}